setup.py
devops/__init__.py
devops/devops.py
devops/tests/__init__.py
devops/tests/test_devops.py
the_devops.egg-info/PKG-INFO
the_devops.egg-info/SOURCES.txt
the_devops.egg-info/dependency_links.txt
the_devops.egg-info/top_level.txt