Metadata-Version: 1.1
Name: the-devops
Version: 1.0.0
Summary: A magic devops package
Home-page: https://github.com/davidjohngee/devops
Author: A shameful project by @davidjohngee
Author-email: david.john.gee@gmail.com
License: UNKNOWN
Platform: UNKNOWN
Classifier: Development Status :: 5 - Production/Stable
Classifier: Intended Audience :: Developers
Classifier: License :: OSI Approved :: Apache Software License
Classifier: Operating System :: OS Independent
Classifier: Programming Language :: Python
Classifier: Programming Language :: Python :: 2.7
Classifier: Topic :: Software Development :: Libraries
Classifier: Topic :: Software Development :: Libraries :: Python Modules
Classifier: Topic :: System :: Networking
